<?xml version="1.0" encoding="utf-8"?> <item><solutions><solution><linktext><![CDATA[Enable in-app product purchases]]></linktext><linkurl><![CDATA[https://docs.microsoft.com/windows/uwp/monetize/enable-in-app-product-purchases]]></linkurl></solution><solution><linktext><![CDATA[In-app purchases and trials]]></linktext><linkurl><![CDATA[https://docs.microsoft.com/windows/uwp/monetize/in-app-purchases-and-trials]]></linkurl></solution><solution><linktext><![CDATA[Enable consumable in-app product purchases]]></linktext><linkurl><![CDATA[https://docs.microsoft.com/windows/uwp/monetize/enable-consumable-in-app-product-purchases]]></linkurl></solution></solutions><supportoptions><supportoption type="Dev Center-CSS-Chat"><title><![CDATA[Chat with Microsoft Support]]></title><description><![CDATA[Chat online with a live Microsoft Support agent.]]></description><linkurl><![CDATA[https://dynamics.microsoft.com/contact-us/]]><![CDATA[" target="_blank" data-tracking-supportoption="Dev Center-CSS-Chat]]></linkurl><icon>/images/partner/startchat.jpg</icon><numbers><numbertitle><![CDATA[]]></numbertitle><numberurl><![CDATA[]]></numberurl><numbertitle><![CDATA[]]></numbertitle><numberurl><![CDATA[]]></numberurl><numbertitle><![CDATA[]]></numbertitle><numberurl><![CDATA[]]></numberurl><numbertitle><![CDATA[]]></numbertitle><numberurl><![CDATA[]]></numberurl><numbertitle><![CDATA[]]></numbertitle><numberurl><![CDATA[]]></numberurl></numbers></supportoption><supportoption type="Developer-CSS-WebSubmission"><title><![CDATA[Submit an incident]]></title><description><![CDATA[Connect with experts to get answers to your questions.]]></description><linkurl><![CDATA[https://partner.microsoft.com/dashboard/incentives/claims/web/support]]><![CDATA[" target="_blank" data-tracking-supportoption="Developer-CSS-WebSubmission]]></linkurl><icon>/images/partner/submitIncident.jpg</icon><numbers><numbertitle><![CDATA[]]></numbertitle><numberurl><![CDATA[]]></numberurl><numbertitle><![CDATA[]]></numbertitle><numberurl><![CDATA[]]></numberurl><numbertitle><![CDATA[]]></numbertitle><numberurl><![CDATA[]]></numberurl><numbertitle><![CDATA[]]></numbertitle><numberurl><![CDATA[]]></numberurl><numbertitle><![CDATA[]]></numbertitle><numberurl><![CDATA[]]></numberurl></numbers></supportoption></supportoptions></item>