<?xml version="1.0" encoding="utf-8"?> <item><solutions> <solution><linktext>Come aggiungere i dati bancari per ricevere gli incentivi Azure</linktext><linkurl><![CDATA[https://support.microsoft.com/help/3073470]]></linkurl></solution> <solution><linktext>Come inviare moduli bancari e fiscali - Azure</linktext><linkurl><![CDATA[https://support.microsoft.com/help/3090503]]></linkurl></solution> <solution><linktext>Dove aggiornare i dati fiscali - Azure</linktext><linkurl><![CDATA[https://support.microsoft.com/help/3011099]]></linkurl></solution>   </solutions><communities> <community><linktext>Community di Microsoft Partner</linktext><linkurl><![CDATA[https://www.microsoftpartnercommunity.com/]]></linkurl><icon>/images/partner/mpn-34.png</icon></community>     </communities><submission><title>Crea un caso di supporto del programma</title><description>Crea un caso di supporto del programma</description><linkurl><![CDATA[http://www.microsoftpartnersupport.com/create-incident?mpnid=Unavailable&email=ociemea@microsoft.com&supporttopicid_l1=Incentivi e pagamento incentivi&supporttopicid_l2=Incentivi per partner&supporttopicid_l3=Azure&locale=it-it&language=it]]></linkurl><linktext>Crea un caso di supporto del programma</linktext><icon>/images/partner/submitIncident.jpg</icon></submission><chat><title></title><description></description><linkurl></linkurl><linktext></linktext><icon></icon></chat><call><title></title><description></description><icon></icon><numbers><numbertitle></numbertitle><numberurl></numberurl><numbertitle></numbertitle><numberurl></numberurl><numbertitle></numbertitle><numberurl></numberurl><numbertitle></numbertitle><numberurl></numberurl></numbers></call></item>