<?xml version="1.0" encoding="utf-8"?> <item><solutions> <solution><linktext>查看 SQL 支持更新网站</linktext><linkurl><![CDATA[http://www.microsoft.com/sqlserver/support/support-updates.aspx]]></linkurl></solution>    <solution><linktext>Microsoft 合作伙伴技术支持  </linktext><linkurl><![CDATA[https://support.microsoft.com/help/4020188  ]]></linkurl></solution> </solutions><communities> <community><linktext>SQL Server 合作伙伴论坛</linktext><linkurl><![CDATA[http://partnersupport.microsoft.com/zh-hans/mpndataplat/forum/mpnsqlsvr?tab=Threads]]><![CDATA[" target="_blank]]></linkurl><icon>/images/partner/mpn-34.png</icon></community> <community><linktext>@SQLServer</linktext><linkurl><![CDATA[http://twitter.com/sqlserver]]><![CDATA[" target="_blank]]></linkurl><icon>/images/partner/twitter-34.png</icon></community> <community><linktext>SQL Server YouTube 视频</linktext><linkurl><![CDATA[http://www.youtube.com/sqlserver]]><![CDATA[" target="_blank]]></linkurl><icon>/images/partner/youtube-34.png</icon></community> <community><linktext>Microsoft SQL Server 支持博客</linktext><linkurl><![CDATA[http://blogs.msdn.com/b/sqlblog/]]><![CDATA[" target="_blank]]></linkurl><icon>/images/partner/rss-blog-34.png</icon></community>  </communities><submission><level id="NetworkMember"><title>创建计划支持案例</title><description>创建计划支持案例</description><linkurl><![CDATA[https://support.microsoft.com/assistedsupportproducts?sd=partner&wfname=partner]]></linkurl><linktext>创建计划支持案例</linktext><icon>/images/partner/submitIncident.jpg</icon></level><level id="MAPS"><title>创建计划支持案例</title><description>创建计划支持案例</description><linkurl><![CDATA[https://support.microsoft.com/assistedsupportproducts?sd=partner&wfname=partner]]></linkurl><linktext>创建计划支持案例</linktext><icon>/images/partner/submitIncident.jpg</icon></level> <level id="Silver"><title>创建计划支持案例</title><description>创建计划支持案例</description><linkurl><![CDATA[https://support.microsoft.com/assistedsupportproducts?sd=partner&wfname=partner]]></linkurl><linktext>创建计划支持案例</linktext><icon>/images/partner/submitIncident.jpg</icon></level> <level id="Gold"><title>创建计划支持案例</title><description>创建计划支持案例</description><linkurl><![CDATA[https://support.microsoft.com/assistedsupportproducts?sd=partner&wfname=partner]]></linkurl><linktext>创建计划支持案例</linktext><icon>/images/partner/submitIncident.jpg</icon></level> <level id="SignatureCloud"><title>创建计划支持案例</title><description>创建计划支持案例</description><linkurl><![CDATA[https://support.microsoft.com/assistedsupportproducts?sd=partner&wfname=partner]]></linkurl><linktext>创建计划支持案例</linktext><icon>/images/partner/submitIncident.jpg</icon></level> <level id="ADR/ADD"><title>创建计划支持案例</title><description>创建计划支持案例</description><linkurl><![CDATA[https://support.microsoft.com/assistedsupportproducts?sd=partner&wfname=partner]]></linkurl><linktext>创建计划支持案例</linktext><icon>/images/partner/submitIncident.jpg</icon></level> <level id="Artemis"><title>创建计划支持案例</title><description>创建计划支持案例</description><linkurl><![CDATA[https://support.microsoft.com/assistedsupportproducts?sd=partner&wfname=partner]]></linkurl><linktext>创建计划支持案例</linktext><icon>/images/partner/submitIncident.jpg</icon></level> </submission><chat> <skill level="NetworkMember">WW.SZH.CS.PAR.PROGMS.MPN</skill> <skill level="MAPS">WW.SZH.CS.PAR.PROGMS.MPN</skill> <skill level="Silver">WW.SZH.CS.PAR.PROGMS.MPN</skill> <skill level="Gold">WW.SZH.CS.PAR.PROGMS.MPN</skill> <skill level="SignatureCloud">WW.SZH.CS.PAR.PROGMS.MPN</skill> <skill level="ADR/ADD">WW.SZH.CS.PAR.PROGMS.MPN</skill> <skill level="Artemis">WW.SZH.CS.PAR.PROGMS.MPN</skill> </chat><call> <level id="NetworkMember"><title></title><description></description><icon></icon><numbers><number></number><number></number><number></number><number></number></numbers></level> <level id="MAPS"><title>致电代理</title><description>与地区服务中心代理电话交谈。</description><icon>/images/partner/callAgent.jpg</icon><numbers><number>800-819-0550 (toll free)</number><number>400-620-0550 (Mobile)</number><number> </number><number> </number></numbers></level> <level id="Silver"><title>致电代理</title><description>与地区服务中心代理电话交谈。</description><icon>/images/partner/callAgent.jpg</icon><numbers><number>800-819-0550 (toll free)</number><number>400-620-0550 (Mobile)</number><number> </number><number> </number></numbers></level> <level id="Gold"><title>致电代理</title><description>与地区服务中心代理电话交谈。</description><icon>/images/partner/callAgent.jpg</icon><numbers><number>800-819-0550 (toll free)</number><number>400-620-0550 (Mobile)</number><number> </number><number> </number></numbers></level> <level id="SignatureCloud"><title>致电代理</title><description>与地区服务中心代理电话交谈。</description><icon>/images/partner/callAgent.jpg</icon><numbers><number>800-819-0550 (toll free)</number><number>400-620-0550 (Mobile)</number><number> </number><number> </number></numbers></level> <level id="ADD/ADR"><title>致电代理</title><description>与地区服务中心代理电话交谈。</description><icon>/images/partner/callAgent.jpg</icon><numbers><number>800-819-0550 (toll free)</number><number>400-620-0550 (Mobile)</number><number> </number><number> </number></numbers></level> <level id="Artemis"><title>致电代理</title><description>与地区服务中心代理电话交谈。</description><icon>/images/partner/callAgent.jpg</icon><numbers><number>800-819-0550 (toll free)</number><number>400-620-0550 (Mobile)</number><number> </number><number> </number></numbers></level> </call></item>