<?xml version="1.0" encoding="utf-8"?> <item><solutions> <solution><linktext>Por que comprar de um Recondicionador Autorizado da Microsoft?</linktext><linkurl><![CDATA[https://www.microsoft.com/refurbishedpcs/buygenuine]]></linkurl></solution>     </solutions><communities> <community><linktext>@MPNSupport</linktext><linkurl><![CDATA[https://twitter.com/MPNSupport]]></linkurl><icon>/images/partner/twitter-34.png</icon></community> <community><linktext>Inscreva-se no canal do YouTube de Suporte a Parceiros do MPN</linktext><linkurl><![CDATA[https://www.youtube.com/user/MSPartnerTech]]></linkurl><icon> /images/partner/youtube-34.png</icon></community> <community><linktext>Comunidade de Parceiros da Microsoft</linktext><linkurl><![CDATA[https://www.microsoftpartnercommunity.com/]]></linkurl><icon>/images/partner/mpn-34.png</icon></community>   </communities><submission><title>Microsoft Action Pack (MAPS)</title><description>O Action Pack oferece software, suporte e benefícios para as empresas que desejam iniciar, desenvolver e ampliar suas práticas da Microsoft em um mundo que prioriza a nuvem e a mobilidade. Vende aproximadamente duas vezes mais volume de nuvem do que os membros da rede, com um conjunto robusto de software que oferece</description><linkurl><![CDATA[https://devicepartner.microsoft.com/assets/collection/Public-Guides---Microsoft-Authorized-Refurbisher-Program#/]]></linkurl><linktext>Obter o Action Pack</linktext><icon>/images/partner/submitIncident.jpg</icon></submission><chat><title></title><description></description><linkurl></linkurl><linktext></linktext><icon></icon></chat><call><title></title><description></description><icon></icon><numbers><numbertitle></numbertitle><numberurl></numberurl><numbertitle></numbertitle><numberurl></numberurl><numbertitle></numbertitle><numberurl></numberurl><numbertitle></numbertitle><numberurl></numberurl></numbers></call></item>