<?xml version="1.0" encoding="utf-8"?> <item><solutions><solution><linktext><![CDATA[Mettre à jour votre profil de partenaire]]></linktext><linkurl><![CDATA[https://docs.microsoft.com/partner-center/update-your-partner-profile]]></linkurl></solution><solution><linktext><![CDATA[Gérer votre compte Espace partenaires]]></linktext><linkurl><![CDATA[https://docs.microsoft.com/partner-center/partner-center-account-setup]]></linkurl></solution></solutions><supportoptions><supportoption type="CSP-CSS-Chat"><title><![CDATA[Démarrer une discussion en ligne]]></title><description><![CDATA[Discutez en ligne avec un agent du Microsoft Support.]]></description><linkurl><![CDATA[https://devicepartner.microsoft.com/assets/detail/device-partner-center-quickstart-guide-new-dpc-supp-fav-docx]]><![CDATA[" target="_blank]]></linkurl><icon>/images/partner/startchat.jpg</icon><numbers><numbertitle><![CDATA[]]></numbertitle><numberurl><![CDATA[]]></numberurl><numbertitle><![CDATA[]]></numbertitle><numberurl><![CDATA[]]></numberurl><numbertitle><![CDATA[]]></numbertitle><numberurl><![CDATA[]]></numberurl><numbertitle><![CDATA[]]></numbertitle><numberurl><![CDATA[]]></numberurl><numbertitle><![CDATA[]]></numbertitle><numberurl><![CDATA[]]></numberurl></numbers></supportoption><supportoption type="RSC-CSS-WebSubmission"><title><![CDATA[Soumettre un incident]]></title><description><![CDATA[Contactez des experts pour obtenir des réponses à vos questions.]]></description><linkurl><![CDATA[]]><![CDATA[" target="_blank]]></linkurl><icon>/images/partner/submitIncident.jpg</icon><numbers><numbertitle><![CDATA[]]></numbertitle><numberurl><![CDATA[]]></numberurl><numbertitle><![CDATA[]]></numbertitle><numberurl><![CDATA[]]></numberurl><numbertitle><![CDATA[]]></numbertitle><numberurl><![CDATA[]]></numberurl><numbertitle><![CDATA[]]></numbertitle><numberurl><![CDATA[]]></numberurl><numbertitle><![CDATA[]]></numbertitle><numberurl><![CDATA[]]></numberurl></numbers></supportoption><supportoption type="RSC-CSS-Phone"><title><![CDATA[Appelez un agent]]></title><description><![CDATA[Parlez par téléphone à un agent du Centre de service régional.]]></description><linkurl><![CDATA[]]><![CDATA[" target="_blank]]></linkurl><icon>/images/partner/callAgent.jpg</icon><numbers><numbertitle><![CDATA[+1 877-453-1317 (en anglais)]]></numbertitle><numberurl><![CDATA[]]></numberurl><numbertitle><![CDATA[]]></numbertitle><numberurl><![CDATA[]]></numberurl><numbertitle><![CDATA[]]></numbertitle><numberurl><![CDATA[]]></numberurl><numbertitle><![CDATA[]]></numbertitle><numberurl><![CDATA[]]></numberurl><numbertitle><![CDATA[]]></numbertitle><numberurl><![CDATA[]]></numberurl></numbers></supportoption><supportoption type="CSP-CSS-Yammer"><title><![CDATA[Microsoft CSP Community]]></title><description><![CDATA[]]></description><linkurl><![CDATA[https://devicepartner.microsoft.com/support]]><![CDATA[" target="_blank]]></linkurl><icon>/images/partner/mpn-34.png</icon><numbers><numbertitle><![CDATA[]]></numbertitle><numberurl><![CDATA[]]></numberurl><numbertitle><![CDATA[]]></numbertitle><numberurl><![CDATA[]]></numberurl><numbertitle><![CDATA[]]></numbertitle><numberurl><![CDATA[]]></numberurl><numbertitle><![CDATA[]]></numbertitle><numberurl><![CDATA[]]></numberurl><numbertitle><![CDATA[]]></numbertitle><numberurl><![CDATA[]]></numberurl></numbers></supportoption></supportoptions></item>