<?xml version="1.0" encoding="utf-8"?> <item><solutions><solution><linktext><![CDATA[Submit a support incident]]></linktext><linkurl><![CDATA[https://support.microsoft.com/assistedsupportproducts]]></linkurl></solution><solution><linktext><![CDATA[Microsoft Partner Network technical benefits summary]]></linktext><linkurl><![CDATA[https://support.microsoft.com/help/2987884]]></linkurl></solution><solution><linktext><![CDATA[Professional Support Options]]></linktext><linkurl><![CDATA[https://support.microsoft.com/gp/offerprophone]]></linkurl></solution><solution><linktext><![CDATA[Compare Support Offerings]]></linktext><linkurl><![CDATA[https://partner.microsoft.com/support/partnersupport]]></linkurl></solution></solutions><supportoptions><supportoption type="PPI-CSS-SupportPortal"><title><![CDATA[Professional Support Options]]></title><description><![CDATA[Professional Support is available as a single “pay-per-incident” (PPI) or a 5-pack of incidents. Professional Support incidents focus on troubleshooting a specific problem, error message, or functionality that is not working as intended for Microsoft products. An incident is defined as a single support issue and the reasonable effort to resolve it. ]]></description><linkurl><![CDATA[https://support.microsoft.com/gp/offerprophone]]><![CDATA[" target="_blank]]></linkurl><icon>/images/partner/submitIncident.jpg</icon><numbers><numbertitle><![CDATA[]]></numbertitle><numberurl><![CDATA[]]></numberurl><numbertitle><![CDATA[]]></numbertitle><numberurl><![CDATA[]]></numberurl><numbertitle><![CDATA[]]></numbertitle><numberurl><![CDATA[]]></numberurl><numbertitle><![CDATA[]]></numbertitle><numberurl><![CDATA[]]></numberurl><numbertitle><![CDATA[]]></numbertitle><numberurl><![CDATA[]]></numberurl></numbers></supportoption></supportoptions></item>