<?xml version="1.0" encoding="utf-8"?> <item><solutions> <solution><linktext>Soporte para Outlook.com</linktext><linkurl><![CDATA[https://support.office.com/article/Get-help-with-Outlook-com-40676AD0-C831-45AC-A023-5BE633BE798D]]></linkurl></solution>   <solution><linktext>Soporte técnico para partners de Microsoft  </linktext><linkurl><![CDATA[https://support.microsoft.com/help/4020188  ]]></linkurl></solution>  </solutions><communities> <community><linktext>Comunidad de Outlook.com</linktext><linkurl><![CDATA[http://answers.microsoft.com/en-us/outlook_com]]></linkurl><icon>/images/partner/mpn-34.png</icon></community> <community><linktext>@Outlook</linktext><linkurl><![CDATA[https://twitter.com/Outlook]]></linkurl><icon>/images/partner/twitter-34.png</icon></community> <community><linktext>Vídeos sobre Outlook.com</linktext><linkurl><![CDATA[https://www.youtube.com/user/MSFTOutlook]]></linkurl><icon>/images/partner/youtube-34.png</icon></community>   </communities><submission><title>Enviar comentarios</title><description>Enviar comentarios</description><linkurl><![CDATA[http://go.microsoft.com/fwlink/?LinkID=255155]]></linkurl><linktext>Enviar comentarios</linktext><icon>/images/partner/submitIncident.jpg</icon></submission><chat><title></title><description></description><linkurl></linkurl><linktext></linktext><icon></icon></chat><call><title>Llamar a un profesional de soporte</title><description>Obtener asistencia telefónica para sus problemas técnicos.</description><icon>/images/partner/callAgent.jpg</icon><numbers><numbertitle> 52 55 47772929   Español</numbertitle><numberurl></numberurl><numbertitle>01 800 123 3353   </numbertitle><numberurl></numberurl><numbertitle>1 305 418 9143 (Larga Distancia)   </numbertitle><numberurl></numberurl><numbertitle></numbertitle><numberurl></numberurl></numbers></call></item>