<?xml version="1.0" encoding="utf-8"?> <item><solutions> <solution><linktext>기술 여정</linktext><linkurl><![CDATA[https://partner.microsoft.com/reach-customers/technical-journeys]]></linkurl></solution> <solution><linktext>기술 사전 판매 및 배포 서비스 이용</linktext><linkurl><![CDATA[https://support.microsoft.com/help/3121537]]></linkurl></solution>    </solutions><communities> <community><linktext>@MPNSupport</linktext><linkurl><![CDATA[https://twitter.com/MPNSupport]]></linkurl><icon>/images/partner/twitter-34.png</icon></community> <community><linktext>MPN 파트너 지원 YouTube 채널 구독</linktext><linkurl><![CDATA[https://www.youtube.com/user/MSPartnerTech]]></linkurl><icon> /images/partner/youtube-34.png</icon></community> <community><linktext>Microsoft 파트너 커뮤니티</linktext><linkurl><![CDATA[https://www.microsoftpartnercommunity.com/]]></linkurl><icon>/images/partner/mpn-34.png</icon></community>   </communities><submission><title>온라인으로 요청서 제출하기</title><description>혜택을 확인하시고 요청서를 제출하십시오.</description><linkurl><![CDATA[https://partner.microsoft.com/support/submission?targetURL=https%3A%2F%2Fsupport.microsoft.com%2Fhelp%2F4476513%3Fwfname%3Dposadvisory]]></linkurl><linktext>혜택을 확인하시고 요청서를 제출하십시오.</linktext><icon>/images/partner/submitIncident.jpg</icon></submission><chat><title></title><description></description><linkurl></linkurl><linktext></linktext><icon></icon></chat><call><title></title><description></description><icon></icon><numbers><numbertitle></numbertitle><numberurl></numberurl><numbertitle></numbertitle><numberurl></numberurl><numbertitle></numbertitle><numberurl></numberurl><numbertitle></numbertitle><numberurl></numberurl></numbers></call></item>