<?xml version="1.0" encoding="utf-8"?> <item><solutions> <solution><linktext>Ottieni supporto tecnico per architettura informativa, distribuzioni e migrazioni di modernizzazione della piattaforma dati.</linktext><linkurl><![CDATA[https://support.microsoft.com/help/4046026]]></linkurl></solution>     </solutions><communities>      </communities><submission><level id="NetworkMember"><title>Aprire una richiesta di assistenza online</title><description>Aprire una richiesta di assistenza</description><linkurl><![CDATA[https://support.microsoft.com/getsupport/hostpage.aspx?oaspworkflow=start_1.0.0.0&wfname=posadvisory&sd=partner&wf=0&mpnid={LOCID}&supporttopicId_L1=&supporttopicId_L2=&supporttopicId_L3=&supporttopicId_L4=&locale=it-it&SupportRegion=it-it]]></linkurl><linktext>Aprire una richiesta di assistenza</linktext><icon>/images/partner/submitIncident.jpg</icon></level><level id="MAPS"><title>Aprire una richiesta di assistenza online</title><description>Aprire una richiesta di assistenza</description><linkurl><![CDATA[https://support.microsoft.com/getsupport/hostpage.aspx?oaspworkflow=start_1.0.0.0&wfname=posadvisory&sd=partner&wf=0&mpnid={LOCID}&supporttopicId_L1=&supporttopicId_L2=&supporttopicId_L3=&supporttopicId_L4=&locale=it-it&SupportRegion=it-it]]></linkurl><linktext>Aprire una richiesta di assistenza</linktext><icon>/images/partner/submitIncident.jpg</icon></level> <level id="Silver"><title>Aprire una richiesta di assistenza online</title><description>Aprire una richiesta di assistenza</description><linkurl><![CDATA[https://support.microsoft.com/getsupport/hostpage.aspx?oaspworkflow=start_1.0.0.0&wfname=posadvisory&sd=partner&wf=0&mpnid={LOCID}&supporttopicId_L1=&supporttopicId_L2=&supporttopicId_L3=&supporttopicId_L4=&locale=it-it&SupportRegion=it-it]]></linkurl><linktext>Aprire una richiesta di assistenza</linktext><icon>/images/partner/submitIncident.jpg</icon></level> <level id="Gold"><title>Aprire una richiesta di assistenza online</title><description>Aprire una richiesta di assistenza</description><linkurl><![CDATA[https://support.microsoft.com/getsupport/hostpage.aspx?oaspworkflow=start_1.0.0.0&wfname=posadvisory&sd=partner&wf=0&mpnid={LOCID}&supporttopicId_L1=&supporttopicId_L2=&supporttopicId_L3=&supporttopicId_L4=&locale=it-it&SupportRegion=it-it]]></linkurl><linktext>Aprire una richiesta di assistenza</linktext><icon>/images/partner/submitIncident.jpg</icon></level> <level id="SignatureCloud"><title>Aprire una richiesta di assistenza online</title><description>Aprire una richiesta di assistenza</description><linkurl><![CDATA[https://support.microsoft.com/getsupport/hostpage.aspx?oaspworkflow=start_1.0.0.0&wfname=posadvisory&sd=partner&wf=0&mpnid={LOCID}&supporttopicId_L1=&supporttopicId_L2=&supporttopicId_L3=&supporttopicId_L4=&locale=it-it&SupportRegion=it-it]]></linkurl><linktext>Aprire una richiesta di assistenza</linktext><icon>/images/partner/submitIncident.jpg</icon></level> <level id="ADR/ADD"><title>Aprire una richiesta di assistenza online</title><description>Aprire una richiesta di assistenza</description><linkurl><![CDATA[https://support.microsoft.com/getsupport/hostpage.aspx?oaspworkflow=start_1.0.0.0&wfname=posadvisory&sd=partner&wf=0&mpnid={LOCID}&supporttopicId_L1=&supporttopicId_L2=&supporttopicId_L3=&supporttopicId_L4=&locale=it-it&SupportRegion=it-it]]></linkurl><linktext>Aprire una richiesta di assistenza</linktext><icon>/images/partner/submitIncident.jpg</icon></level> <level id="Artemis"><title>Aprire una richiesta di assistenza online</title><description>Aprire una richiesta di assistenza</description><linkurl><![CDATA[https://support.microsoft.com/getsupport/hostpage.aspx?oaspworkflow=start_1.0.0.0&wfname=posadvisory&sd=partner&wf=0&mpnid={LOCID}&supporttopicId_L1=&supporttopicId_L2=&supporttopicId_L3=&supporttopicId_L4=&locale=it-it&SupportRegion=it-it]]></linkurl><linktext>Aprire una richiesta di assistenza</linktext><icon>/images/partner/submitIncident.jpg</icon></level> </submission><chat> <skill level="NetworkMember"></skill> <skill level="MAPS"></skill> <skill level="Silver"></skill> <skill level="Gold"></skill> <skill level="SignatureCloud"></skill> <skill level="ADR/ADD"></skill> <skill level="Artemis"></skill> </chat><call> <level id="NetworkMember"><title>Chiama un agente del supporto</title><description>Ottieni assistenza telefonica per i tuoi problemi tecnici.</description><icon>/images/partner/callAgent.jpg</icon><numbers><number>39 02 38 59 14 44   Italiano</number><number> </number><number> </number><number> </number></numbers></level> <level id="MAPS"><title>Chiama un agente del supporto</title><description>Ottieni assistenza telefonica per i tuoi problemi tecnici.</description><icon>/images/partner/callAgent.jpg</icon><numbers><number>39 02 38 59 14 44   Italiano</number><number> </number><number> </number><number> </number></numbers></level> <level id="Silver"><title>Chiama un agente del supporto</title><description>Ottieni assistenza telefonica per i tuoi problemi tecnici.</description><icon>/images/partner/callAgent.jpg</icon><numbers><number>39 02 38 59 14 44   Italiano</number><number> </number><number> </number><number> </number></numbers></level> <level id="Gold"><title>Chiama un agente del supporto</title><description>Ottieni assistenza telefonica per i tuoi problemi tecnici.</description><icon>/images/partner/callAgent.jpg</icon><numbers><number>39 02 38 59 14 44   Italiano</number><number> </number><number> </number><number> </number></numbers></level> <level id="SignatureCloud"><title>Chiama un agente del supporto</title><description>Ottieni assistenza telefonica per i tuoi problemi tecnici.</description><icon>/images/partner/callAgent.jpg</icon><numbers><number>39 02 38 59 14 44   Italiano</number><number> </number><number> </number><number> </number></numbers></level> <level id="ADR/ADD"><title>Chiama un agente del supporto</title><description>Ottieni assistenza telefonica per i tuoi problemi tecnici.</description><icon>/images/partner/callAgent.jpg</icon><numbers><number>39 02 38 59 14 44   Italiano</number><number> </number><number> </number><number> </number></numbers></level> <level id="Artemis"><title>Chiama un agente del supporto</title><description>Ottieni assistenza telefonica per i tuoi problemi tecnici.</description><icon>/images/partner/callAgent.jpg</icon><numbers><number>39 02 38 59 14 44   Italiano</number><number> </number><number> </number><number> </number></numbers></level> </call></item>