<?xml version="1.0" encoding="utf-8"?> <item><solutions><solution><linktext><![CDATA[Cloud Solution Provider – Verträge, Preislisten und Angebote]]></linktext><linkurl><![CDATA[https://docs.microsoft.com/partner-center/csp-documents-and-learning-resources]]></linkurl></solution><solution><linktext><![CDATA[PartnerSource-Kontaktadressen]]></linktext><linkurl><![CDATA[https://mbs.microsoft.com/PartnerSource/global/Help/Help/ContactUs ]]></linkurl></solution><solution><linktext><![CDATA[Dynamics PartnerSource]]></linktext><linkurl><![CDATA[https://mbs.microsoft.com/partnersource]]></linkurl></solution></solutions><supportoptions><supportoption type="MBS-Ops-WebSubmission"><title>Vorfall absenden</title><description>Kommunizieren Sie mit Experten, um Antworten auf Ihre Fragen zu erhalten.</description><linkurl><![CDATA[https://mbs2.microsoft.com/Support/OperationsIncidents.aspx?Mode=Create]]><![CDATA[" target="_blank]]></linkurl><icon>/images/partner/submitIncident.jpg</icon><numbers><numbertitle></numbertitle><numberurl></numberurl><numbertitle></numbertitle><numberurl></numberurl><numbertitle></numbertitle><numberurl></numberurl><numbertitle></numbertitle><numberurl></numberurl><numbertitle></numbertitle><numberurl></numberurl></numbers></supportoption></supportoptions></item>