<?xml version="1.0" encoding="utf-8"?> <item><solutions><solution><linktext><![CDATA[Exibir Soluções Recomendadas para este tópico no Partner Center]]></linktext><linkurl><![CDATA[https://partner.microsoft.com/support/v2/?stage=2&topicid=eb74583c-61b3-2124-bffc-00920e0ae772]]></linkurl></solution></solutions><supportoptions><supportoption type="32635659-CSS-WebSubmission"><title><![CDATA[Enviar um incidente]]></title><description><![CDATA[Conecte-se com especialistas para obter respostas às suas perguntas.]]></description><linkurl><![CDATA[https://partner.microsoft.com/support/v2/?stage=2&topicid=eb74583c-61b3-2124-bffc-00920e0ae772]]><![CDATA[" target="_blank]]></linkurl><icon>/images/partner/submitIncident.jpg</icon><numbers><numbertitle><![CDATA[]]></numbertitle><numberurl><![CDATA[]]></numberurl><numbertitle><![CDATA[]]></numbertitle><numberurl><![CDATA[]]></numberurl><numbertitle><![CDATA[]]></numbertitle><numberurl><![CDATA[]]></numberurl><numbertitle><![CDATA[]]></numbertitle><numberurl><![CDATA[]]></numberurl><numbertitle><![CDATA[]]></numbertitle><numberurl><![CDATA[]]></numberurl></numbers></supportoption></supportoptions></item>