<?xml version="1.0" encoding="utf-8"?> <item><solutions><solution><linktext><![CDATA[Guía de migración de PMC al Centro de partners]]></linktext><linkurl><![CDATA[https://docs.microsoft.com/partner-center/guide-to-migration]]></linkurl></solution><solution><linktext><![CDATA[Antes de migrar desde Partner Membership Center (PMC) al Centro de partners (PC): guía paso a paso]]></linktext><linkurl><![CDATA[https://support.microsoft.com/help/4503591]]></linkurl></solution><solution><linktext><![CDATA[Move multiple company’s Partner Membership Center (PMC) accounts to Partner center (PC)]]></linktext><linkurl><![CDATA[https://docs.microsoft.com/partner-center/move-multiple-companies]]></linkurl></solution><solution><linktext><![CDATA[Comprobar la cuenta el Centro de partners]]></linktext><linkurl><![CDATA[https://docs.microsoft.com/partner-center/verification-responses]]></linkurl></solution><solution><linktext><![CDATA[Creación del directorio en Azure AD]]></linktext><linkurl><![CDATA[https://docs.microsoft.com/azure/active-directory/fundamentals/add-custom-domain#create-your-directory-in-azure-ad]]></linkurl></solution></solutions><supportoptions><supportoption type="PartnerCenter-CSS-WebSubmission"><title><![CDATA[Crear un caso de soporte técnico del programa]]></title><description><![CDATA[Crear caso de soporte técnico del programa]]></description><linkurl><![CDATA[https://partner.microsoft.com/dashboard/support/servicerequests/create]]><![CDATA[" target="_blank]]></linkurl><icon>/images/partner/submitIncident.jpg</icon><numbers><numbertitle><![CDATA[]]></numbertitle><numberurl><![CDATA[]]></numberurl><numbertitle><![CDATA[]]></numbertitle><numberurl><![CDATA[]]></numberurl><numbertitle><![CDATA[]]></numbertitle><numberurl><![CDATA[]]></numberurl><numbertitle><![CDATA[]]></numbertitle><numberurl><![CDATA[]]></numberurl><numbertitle><![CDATA[]]></numbertitle><numberurl><![CDATA[]]></numberurl></numbers></supportoption></supportoptions></item>